pycurl_requestx/__init__.py
pycurl_requestx/async_client.py
pycurl_requestx/exceptions.py
pycurl_requestx/utils.py
pycurl_requestx/version.py
pycurl_requestx-0.1.1.dist-info/LICENSE
pycurl_requestx-0.1.1.dist-info/METADATA
pycurl_requestx-0.1.1.dist-info/WHEEL
pycurl_requestx-0.1.1.dist-info/top_level.txt
pycurl_requestx-0.1.1.dist-info/RECORD
